deptypes/__init__.py
deptypes/py.typed
deptypes-0.1.0.dist-info/METADATA
deptypes-0.1.0.dist-info/WHEEL
deptypes-0.1.0.dist-info/RECORD
