Metadata-Version: 2.4
Name: deptypes
Version: 0.1.0
Summary: Experiments with dependent typing in Python
Author-email: Alejandro Piad <apiad@apiad.net>
Requires-Python: >=3.13
